tool/__init__.pyi
google_auth_oauthlib_stubs-1.2.0.dist-info/METADATA
google_auth_oauthlib_stubs-1.2.0.dist-info/WHEEL
google_auth_oauthlib_stubs-1.2.0.dist-info/top_level.txt
google_auth_oauthlib_stubs-1.2.0.dist-info/RECORD
